examples/full.py
examples/one_by_one.py
examples/one_by_one_legacy.py
tests/__init__.py
tests/conftest.py
tests/test_client_init.py
tests/test_paralles_run.py
yaspeedtest/__init__.py
yaspeedtest/client.py
yaspeedtest/types.py
yaspeedtest-0.1.6.dist-info/licenses/LICENSE
yaspeedtest-0.1.6.dist-info/licenses/NOTICE
yaspeedtest-0.1.6.dist-info/METADATA
yaspeedtest-0.1.6.dist-info/WHEEL
yaspeedtest-0.1.6.dist-info/top_level.txt
yaspeedtest-0.1.6.dist-info/RECORD
