Metadata-Version: 2.4
Name: yaspeedtest
Version: 0.1.6
Summary: Async client that allows you to measure internet speed based on Yandex Internetometer
Author-email: Nikita Erilov <minitwiks@gmail.com>
License: Apache-2.0
Project-URL: Homepage, https://github.com/ErilovNikita/yaspeedtest
Project-URL: Repository, https://github.com/ErilovNikita/yaspeedtest
Project-URL: Documentation, https://github.com/ErilovNikita/yaspeedtest/README.md
Classifier: Development Status :: 5 - Production/Stable
Classifier: Programming Language :: Python
Classifier: Programming Language :: Python :: 3.11
Classifier: Programming Language :: Python :: 3.12
Classifier: Programming Language :: Python :: 3.13
Classifier: Programming Language :: Python :: 3.14
Requires-Python: >=3.11
License-File: LICENSE
License-File: NOTICE
Requires-Dist: requests>=2.28
Requires-Dist: aiohttp==3.12.15
Requires-Dist: asyncio==4.0.0
Requires-Dist: pydantic>=2.11.9
Provides-Extra: dev
Requires-Dist: build==1.3.0; extra == "dev"
Requires-Dist: twine==6.2.0; extra == "dev"
Requires-Dist: pytest==9.0.1; extra == "dev"
Requires-Dist: pytest-asyncio==1.3.0; extra == "dev"
Requires-Dist: aioresponses==0.7.8; extra == "dev"
Requires-Dist: pytest-cov==7.0.0; extra == "dev"
Dynamic: license-file
